{
  "routes": [
    {
      "path": "/webapp/resources",
      "target": {
        "type": "service",
        "name": "sapui5",
        "entryPath": "/resources",
        "version": "1.52.49"
      },
      "description": "SAPUI5 Resources"
    },
    {
      "path": "/webapp/test-resources",
      "target": {
        "type": "service",
        "name": "sapui5",
        "entryPath": "/test-resources",
        "version": "1.52.49"
      },
      "description": "SAPUI5 Test Resources"
    },
    {
      "path": "/resources",
      "target": {
        "type": "service",
        "name": "sapui5",
        "entryPath": "/resources",
        "version": "1.52.49"
      },
      "description": "SAPUI5 Resources"
    },
    {
      "path": "/test-resources",
      "target": {
        "type": "service",
        "name": "sapui5",
        "entryPath": "/test-resources",
        "version": "1.52.49"
      },
      "description": "SAPUI5 Test Resources"
    },
    {
      "path": "/sap/opu/odata/sap/ZSCHVAL_PROJ_SRV",
      "target": {
        "type": "destination",
        "name": "vsb_zschval_proj_odata"
      },
      "description": "odata service"
    }    
  ],
  "welcomeFile": "/webapp/test/flpSandbox.html",
  "sendWelcomeFileRedirect": true
}